LICENSE
setup.py
simplesettings/__init__.py
simplesettings.egg-info/PKG-INFO
simplesettings.egg-info/SOURCES.txt
simplesettings.egg-info/dependency_links.txt
simplesettings.egg-info/top_level.txt