Metadata-Version: 1.0
Name: simplesettings
Version: 0.5
Summary: Simple settings initialization
Home-page: http://code.google.com/p/simplesettings/
Author: Open Source Applications Foundation
Author-email: tools-dev@osafoundation.org
License: http://www.apache.org/licenses/LICENSE-2.0
Platform: Any
Classifier: Development Status :: 4 - Beta
Classifier: Environment :: Console
Classifier: Intended Audience :: Developers
Classifier: License :: OSI Approved :: Apache Software License
Classifier: Operating System :: OS Independent
Classifier: Topic :: Software Development :: Libraries :: Python Modules
